Deepurify/Infer_uitls.py
Deepurify/__init__.py
Deepurify/binning.py
Deepurify/clean_func.py
Deepurify/cli.py
Deepurify/decontamination.py
Deepurify/iter_clean.py
Deepurify/version.py
Deepurify/Dataset/SequenceDataset.py
Deepurify/Dataset/__init__.py
Deepurify/Model/Convolutions.py
Deepurify/Model/Embedding.py
Deepurify/Model/EncoderModels.py
Deepurify/Model/FormerLayers.py
Deepurify/Model/Loss.py
Deepurify/Model/__init__.py
Deepurify/Train/Scheduler.py
Deepurify/Train/TrainUtils.py
Deepurify/Train/__init__.py
Deepurify/Utils/BuildFilesUtils.py
Deepurify/Utils/CallGenesUtils.py
Deepurify/Utils/DataUtils.py
Deepurify/Utils/FilterContamUtils.py
Deepurify/Utils/HmmUtils.py
Deepurify/Utils/IOUtils.py
Deepurify/Utils/KMeans.py
Deepurify/Utils/LabelBinsUtils.py
Deepurify/Utils/ProdigalUtils.py
Deepurify/Utils/RunCMDUtils.py
Deepurify/Utils/SelectBinsUitls.py
Deepurify/Utils/SequenceUtils.py
Deepurify/Utils/__init__.py
Deepurify-2.4.3.dist-info/LICENSE
Deepurify-2.4.3.dist-info/METADATA
Deepurify-2.4.3.dist-info/WHEEL
Deepurify-2.4.3.dist-info/entry_points.txt
Deepurify-2.4.3.dist-info/top_level.txt
Deepurify-2.4.3.dist-info/RECORD
