Metadata-Version: 2.1
Name: Deepurify
Version: 2.4.3
Summary: The purification tool for improving the quality of MAGs.
Home-page: UNKNOWN
Author: Bohao Zou
Author-email: csbhzou@comp.hkbu.edu.hk
License: UNKNOWN
Platform: UNKNOWN
Requires-Python: >=3.8
License-File: LICENSE
Requires-Dist: func-timeout (==4.3.5)
Requires-Dist: psutil (==5.9.8)
Requires-Dist: checkm2-modified (==1.0.2)
Requires-Dist: numpy (==1.23.5)
Requires-Dist: scipy (==1.8.0)
Requires-Dist: pandas (==1.4.0)
Requires-Dist: scikit-learn (==0.23.2)
Requires-Dist: semibin (==2.1.0)
